_intuned_runtime_internal/__init__.py
_intuned_runtime_internal/backend_functions/__init__.py
_intuned_runtime_internal/backend_functions/_call_backend_function.py
_intuned_runtime_internal/backend_functions/get_auth_session_parameters.py
_intuned_runtime_internal/browser/__init__.py
_intuned_runtime_internal/browser/extensions/__init__.py
_intuned_runtime_internal/browser/extensions/helpers.py
_intuned_runtime_internal/browser/extensions/intuned_extension.py
_intuned_runtime_internal/browser/extensions/intuned_extension_server.py
_intuned_runtime_internal/browser/helpers.py
_intuned_runtime_internal/browser/launch_browser.py
_intuned_runtime_internal/browser/launch_camoufox.py
_intuned_runtime_internal/browser/launch_chromium.py
_intuned_runtime_internal/browser/state.py
_intuned_runtime_internal/browser/storage_state.py
_intuned_runtime_internal/browser/tabs.py
_intuned_runtime_internal/constants.py
_intuned_runtime_internal/context/__init__.py
_intuned_runtime_internal/context/context.py
_intuned_runtime_internal/env.py
_intuned_runtime_internal/errors/__init__.py
_intuned_runtime_internal/errors/auth_session_errors.py
_intuned_runtime_internal/errors/run_api_errors.py
_intuned_runtime_internal/errors/trace_errors.py
_intuned_runtime_internal/helpers/__init__.py
_intuned_runtime_internal/helpers/__test__/__init__.py
_intuned_runtime_internal/helpers/__test__/test_extensions.py
_intuned_runtime_internal/helpers/attempt_store.py
_intuned_runtime_internal/helpers/extend_payload.py
_intuned_runtime_internal/helpers/extend_timeout.py
_intuned_runtime_internal/helpers/extensions.py
_intuned_runtime_internal/helpers/get_ai_gateway_config.py
_intuned_runtime_internal/helpers/get_auth_session_parameters.py
_intuned_runtime_internal/helpers/persistent_store.py
_intuned_runtime_internal/helpers/tests/test_persistent_storage.py
_intuned_runtime_internal/py.typed
_intuned_runtime_internal/run/__init__.py
_intuned_runtime_internal/run/intuned_settings.py
intuned_runtime-1.3.17.dist-info/METADATA
intuned_runtime-1.3.17.dist-info/WHEEL
intuned_runtime-1.3.17.dist-info/entry_points.txt
intuned_runtime-1.3.17.dist-info/licenses/LICENSE
intuned_runtime-1.3.17.dist-info/RECORD
