Metadata-Version: 2.4
Name: intuned-runtime
Version: 1.3.17
Summary: Runtime SDK that powers browser automation projects running on Intuned
License: Elastic-2.0
License-File: LICENSE
Keywords: runtime,intuned
Author: Intuned Developers
Author-email: engineering@intunedhq.com
Requires-Python: >=3.9,<4.0
Classifier: License :: Other/Proprietary License
Classifier: Operating System :: OS Independent
Classifier: Programming Language :: Python :: 3
Classifier: Programming Language :: Python :: 3.9
Classifier: Programming Language :: Python :: 3.10
Classifier: Programming Language :: Python :: 3.11
Classifier: Programming Language :: Python :: 3.12
Classifier: Programming Language :: Python :: 3.13
Classifier: Programming Language :: Python :: 3.14
Requires-Dist: aiofiles (>=24.1.0,<25.0.0)
Requires-Dist: arguably (>=1.3.0,<2.0.0)
Requires-Dist: browserforge[all]
Requires-Dist: camoufox[geoip] (>=0.4.11,<0.5.0)
Requires-Dist: gitpython (>=3.1.43,<4.0.0)
Requires-Dist: httpx (>=0.23.0,<1)
Requires-Dist: jsonc-parser (>=1.1.5,<2.0.0)
Requires-Dist: more-termcolor (>=1.1.3,<2.0.0)
Requires-Dist: numpy (<2.0.0)
Requires-Dist: pathspec (>=0.12.1,<0.13.0)
Requires-Dist: pydantic (>=2.10.6,<3.0.0)
Requires-Dist: pyright (>=1.1.387,<2.0.0)
Requires-Dist: python-dotenv (==1.0.1)
Requires-Dist: pytimeparse (>=1.1.8,<2.0.0)
Requires-Dist: pyyaml (>=6.0.3,<7.0.0)
Requires-Dist: questionary (>=2.1.1,<3.0.0)
Requires-Dist: readchar (>=4.2.1,<5.0.0)
Requires-Dist: requests (>=2.32.3,<3.0.0)
Requires-Dist: rich (>=14.1.0,<15.0.0)
Requires-Dist: ruff (>=0.7.2,<0.8.0)
Requires-Dist: semver (>=3.0.4,<4.0.0)
Requires-Dist: tenacity (>=8.5.0,<9.0.0)
Requires-Dist: toml (>=0.10.2,<0.11.0)
Requires-Dist: waitress (>=3.0.1,<4.0.0)
